bitcoin/__init__.py
bitcoin/ecc.py
bitcoin/helper.py
bitcoin/op.py
bitcoin/wallet.py
bitcoinlantern/__init__.py
bitcoinlantern/bitcoin/__init__.py
bitcoinlantern/bitcoin/ecc.py
bitcoinlantern/bitcoin/helper.py
bitcoinlantern/bitcoin/op.py
bitcoinlantern/bitcoin/script.py
bitcoinlantern/bitcoin/tx.py
bitcoinlantern/bitcoin/wallet.py
bitcoinlantern/rpc/__init__.py
bitcoinlantern/rpc/connection.py
bitcoinlantern/rpc/exceptions.py
bitcoinlantern/rpc/proxy.py
rpc/__init__.py
rpc/connection.py
rpc/exceptions.py
rpc/proxy.py
bitcoinlantern-0.1.5.dist-info/LICENSE
bitcoinlantern-0.1.5.dist-info/METADATA
bitcoinlantern-0.1.5.dist-info/WHEEL
bitcoinlantern-0.1.5.dist-info/top_level.txt
bitcoinlantern-0.1.5.dist-info/RECORD
